<?xml version="1.0" encoding="UTF-8"?>
<beans xmlns="http://www.springframework.org/schema/beans"
	xmlns:xsi="http://www.w3.org/2001/XMLSchema-instance" xmlns:int="http://www.springframework.org/schema/integration"
	xmlns:int-ftp="http://www.springframework.org/schema/integration/ftp"
	xmlns:task="http://www.springframework.org/schema/task" xmlns:int-http="http://www.springframework.org/schema/integration/http"
	xsi:schemaLocation="http://www.springframework.org/schema/integration/http http://www.springframework.org/schema/integration/http/spring-integration-http-3.0.xsd
		http://www.springframework.org/schema/integration/ftp http://www.springframework.org/schema/integration/ftp/spring-integration-ftp.xsd
		http://www.springframework.org/schema/integration http://www.springframework.org/schema/integration/spring-integration.xsd
		http://www.springframework.org/schema/task http://www.springframework.org/schema/task/spring-task.xsd
		http://www.springframework.org/schema/beans http://www.springframework.org/schema/beans/spring-beans.xsd">

	<int:chain id="indexerChain5" input-channel="indexRequestChannel5" output-channel="indexChannel5" >
		
		<int:header-enricher>
			<int:header name="indexName" expression="'${elasticsearch.index.thb.prefix}' + headers.jobId" overwrite="true" />
			<int:header name="indexDate" expression="headers.jobDate" />
			<int:header name="fxBatchSize" value="${loader.fx.fxBatchSize}" />
		</int:header-enricher>
		<int:service-activator ref="indexerService" method="createIndex" />
		<!-- <int:service-activator ref="indexBuilderService" method="buildAlphaFactors" /> -->
		<int:service-activator ref="indexBuilderService" method="createFXIndex" />
		<int:service-activator ref="indexerService" method="flush" />
	</int:chain>

	<int:channel id="indexChannel5" />
	<int:channel id="loggingChannel5" />
	<int:channel id="errorLoggerChannel5"/>	
	<int:channel id="failedLogger5"/>
	<int:publish-subscribe-channel id="aggregationCompleteChannel5"/>
		
	
	
	<!-- Split on tickers for multi-threading -->
	<int:splitter id="tickerSplitter5" input-channel="indexChannel5"
	output-channel="indexTickerChannel5" ref="indexBuilderService" method="readTickers" />
	
		<!-- Load Data -->
 	<int:chain 
 		id="indexDataChain5"
		input-channel="indexTickerChannel5"
		output-channel="tickerAggregatorChannel5">

		<int:header-enricher>
			<int:error-channel value="indexErrorChannel5"/>
		</int:header-enricher>	
		
		<int:service-activator ref="indexBuilderService" method="index">
			<int:request-handler-advice-chain >
				<ref bean="retryAdvice5"/>
			</int:request-handler-advice-chain>
		</int:service-activator>
	</int:chain>
	
	
	<!-- Indexing Error Handling -->
	<int:chain 
		id="indexErrorHandlingChain5"
		input-channel="indexErrorChannel5" 
		output-channel="tickerAggregatorChannel5">		
			
			<int:transformer expression="payload.failedMessage"/>
						
			<int:enricher>
				<int:property name="indexed" value="false"/>
			</int:enricher>							
	</int:chain>
	
	<int:aggregator id="tickerAggregtor5" 
		input-channel="tickerAggregatorChannel5"
	 	output-channel="aggregationCompleteChannel5"
		correlation-strategy-expression="headers.jobId"
		release-strategy-expression="#this.size() == #this[0].headers.sequenceSize">
	</int:aggregator>
	
	<int:router	input-channel="aggregationCompleteChannel5" 
		ref="indexBuilderService"
		method="isJobSuccessful">
				
    	<int:mapping value="true" channel="indexRequestChannel6"/>
    	<int:mapping value="false" channel="failedJobChannel5"/>
    	    	
	</int:router>
	
	<!--  Job Completed successfully, create index and remove old indexes -->
	<int:chain input-channel="createAlias5" output-channel="loggingChannel5">
		<int:service-activator ref="indexerService"
			method="createIndexAlias" />
		<int:service-activator ref="indexBuilderService"
			method="deleteOldIndexes" />
	</int:chain>

	
	<int:logging-channel-adapter channel="loggingChannel5" level="INFO" expression=" 'Job Complete ' + payload.toString()" />
		
		<!-- Job failed -->
	<int:header-enricher input-channel="failedJobChannel5" output-channel="failedLogger5">
		<int:header name="failedJob" value="true"/>
	</int:header-enricher>	
		
	<int:logging-channel-adapter channel="failedLogger5" level="INFO" expression=" 'Job Failed ' + payload.toString()"/>
	
	
	<!-- Channel definitions -->
	<task:executor id="indexerTaskExecutor5" pool-size="${loader.threads}" queue-capacity="100" rejection-policy="CALLER_RUNS" />
	<task:executor id="indexerRequestChannelExecutor5" pool-size="1" queue-capacity="1" rejection-policy="DISCARD" />

	<int:channel id="indexRequestChannel5">
		<int:dispatcher task-executor="indexerRequestChannelExecutor5" />
	</int:channel>
	
	<int:channel id="indexTickerChannel5" datatype="com.wmsi.sgx.model.integration.CompanyInputRecord">	
		<int:dispatcher task-executor="indexerTaskExecutor5" />
	</int:channel>

	<int:channel id="tickerAggregatorChannel5">
		<int:interceptors>
			<int:wire-tap channel="statusLoggingChannel5" />
		</int:interceptors>
	</int:channel>
	
	<int:channel id="statusLoggingChannel5"/>	
	<int:logging-channel-adapter channel="statusLoggingChannel5" level="INFO" expression=" 'Processing ' + headers.sequenceNumber + ' of ' + headers.sequenceSize"/>
	
	<int:channel id="indexErrorChannel5">
		<int:interceptors>
			<int:wire-tap channel="errorLoggerChannel5"/>
		</int:interceptors>
	</int:channel>
	
	<!--  Error Logging -->
	<int:channel id="errorLoggerChannel5"/>		
	<int:service-activator input-channel="errorLoggerChannel5" ref="loggerAdapter" method="error"/>
	<bean id="loggerAdapter1" class="com.wmsi.sgx.logging.integration.IntegrationLoggerAdapter"/>
	
	<!-- Retry Handler -->
	<bean id="retryAdvice5" class="org.springframework.integration.handler.advice.RequestHandlerRetryAdvice">
		<property name="retryTemplate">
			<bean id="retryTemplate5" class="org.springframework.retry.support.RetryTemplate">	
				<property name="retryPolicy">
					<bean class="org.springframework.retry.policy.SimpleRetryPolicy">
						<property name="maxAttempts" value="4" />
					</bean>
				</property>
				<property name="backOffPolicy">
					<bean class="org.springframework.retry.backoff.ExponentialBackOffPolicy">
						<property name="initialInterval" value="1000" />
						<property name="multiplier" value="5" />
					</bean>
				</property>
			</bean>			
		</property>
		<property name="recoveryCallback">
			<bean
				class="org.springframework.integration.handler.advice.ErrorMessageSendingRecoverer">
				<constructor-arg ref="indexErrorChannel5" />
			</bean>
		</property>
	</bean>


</beans>
